StateEngine/__init__.py
StateEngine/_common_utils.py
StateEngine/_errors.py
StateEngine/_stateengine.py
python_stateengine-0.0.1a1.dist-info/LICENSE
python_stateengine-0.0.1a1.dist-info/METADATA
python_stateengine-0.0.1a1.dist-info/WHEEL
python_stateengine-0.0.1a1.dist-info/top_level.txt
python_stateengine-0.0.1a1.dist-info/RECORD
