Metadata-Version: 2.1
Name: python-stateengine
Version: 0.0.1a1
Summary: Finite State Machines in Pure Python!
Author-email: Ayman Imtyaz <aymanimtyaz@gmail.com>
License: MIT License        
Project-URL: Homepage, https://github.com/aymanimtyaz/StateEngine
Project-URL: Bug Tracker, https://github.com/aymanimtyaz/StateEngine/issues
Classifier: Programming Language :: Python :: 3
Classifier: License :: OSI Approved :: MIT License
Classifier: Operating System :: OS Independent
Requires-Python: >=3.7
License-File: LICENSE
